smurtls/__init__.py
smurtls/data.py
smurtls-0.1a12.dist-info/METADATA
smurtls-0.1a12.dist-info/WHEEL
smurtls-0.1a12.dist-info/top_level.txt
smurtls-0.1a12.dist-info/RECORD
