Metadata-Version: 2.1
Name: smurtls
Version: 0.1a12
Summary: Collection of useful classes and functions
Author: Jan P. Hummel
Author-email: jan.hummel@med.uni-muenchen.de
Classifier: Programming Language :: Python :: 3
Classifier: License :: OSI Approved :: MIT License
Classifier: Operating System :: OS Independent
Classifier: Topic :: Utilities
Requires-Dist: pandas
Requires-Dist: numpy
Requires-Dist: scikit-learn
Requires-Dist: lifelines
